NiukeAnquanGongchengshiQiuzhiJingyanFenxiang20212022Fix1/README.md
NiukeAnquanGongchengshiQiuzhiJingyanFenxiang20212022Fix1/__init__.py
NiukeAnquanGongchengshiQiuzhiJingyanFenxiang20212022Fix1/__main__.py
NiukeAnquanGongchengshiQiuzhiJingyanFenxiang20212022Fix1/file.epub
NiukeAnquanGongchengshiQiuzhiJingyanFenxiang20212022Fix1/index.html
NiukeAnquanGongchengshiQiuzhiJingyanFenxiang20212022Fix1/css/__init__.py
NiukeAnquanGongchengshiQiuzhiJingyanFenxiang20212022Fix1/css/annotations.css
NiukeAnquanGongchengshiQiuzhiJingyanFenxiang20212022Fix1/css/main.css
NiukeAnquanGongchengshiQiuzhiJingyanFenxiang20212022Fix1/css/normalize.css
NiukeAnquanGongchengshiQiuzhiJingyanFenxiang20212022Fix1/css/popup.css
NiukeAnquanGongchengshiQiuzhiJingyanFenxiang20212022Fix1/font/__init__.py
NiukeAnquanGongchengshiQiuzhiJingyanFenxiang20212022Fix1/font/fontello.eot
NiukeAnquanGongchengshiQiuzhiJingyanFenxiang20212022Fix1/font/fontello.svg
NiukeAnquanGongchengshiQiuzhiJingyanFenxiang20212022Fix1/font/fontello.ttf
NiukeAnquanGongchengshiQiuzhiJingyanFenxiang20212022Fix1/font/fontello.woff
NiukeAnquanGongchengshiQiuzhiJingyanFenxiang20212022Fix1/img/__init__.py
NiukeAnquanGongchengshiQiuzhiJingyanFenxiang20212022Fix1/img/annotator-glyph-sprite.png
NiukeAnquanGongchengshiQiuzhiJingyanFenxiang20212022Fix1/img/annotator-icon-sprite.png
NiukeAnquanGongchengshiQiuzhiJingyanFenxiang20212022Fix1/img/apple-touch-icon.png
NiukeAnquanGongchengshiQiuzhiJingyanFenxiang20212022Fix1/img/cancelfullscreen.png
NiukeAnquanGongchengshiQiuzhiJingyanFenxiang20212022Fix1/img/close.png
NiukeAnquanGongchengshiQiuzhiJingyanFenxiang20212022Fix1/img/fullscreen.png
NiukeAnquanGongchengshiQiuzhiJingyanFenxiang20212022Fix1/img/loader.gif
NiukeAnquanGongchengshiQiuzhiJingyanFenxiang20212022Fix1/img/menu-icon.png
NiukeAnquanGongchengshiQiuzhiJingyanFenxiang20212022Fix1/img/save.png
NiukeAnquanGongchengshiQiuzhiJingyanFenxiang20212022Fix1/img/saved.png
niuke_anquan_gongchengshi_qiuzhi_jingyan_fenxiang_2021_2022_fix1-2025.3.25.0.dist-info/METADATA
niuke_anquan_gongchengshi_qiuzhi_jingyan_fenxiang_2021_2022_fix1-2025.3.25.0.dist-info/WHEEL
niuke_anquan_gongchengshi_qiuzhi_jingyan_fenxiang_2021_2022_fix1-2025.3.25.0.dist-info/entry_points.txt
niuke_anquan_gongchengshi_qiuzhi_jingyan_fenxiang_2021_2022_fix1-2025.3.25.0.dist-info/top_level.txt
niuke_anquan_gongchengshi_qiuzhi_jingyan_fenxiang_2021_2022_fix1-2025.3.25.0.dist-info/RECORD
